danceshoppe/__init__.py
danceshoppe-0.1.0.dist-info/METADATA
danceshoppe-0.1.0.dist-info/WHEEL
danceshoppe-0.1.0.dist-info/top_level.txt
danceshoppe-0.1.0.dist-info/RECORD
