Metadata-Version: 2.4
Name: danceshoppe
Version: 0.1.0
Summary: Python package for DanceShoppe
Author-email: Your Name <your.email@example.com>
Project-URL: Homepage, https://example.com
Project-URL: Bug Tracker, https://example.com/issues
Classifier: Programming Language :: Python :: 3
Classifier: License :: OSI Approved :: MIT License
Classifier: Operating System :: OS Independent
Requires-Python: >=3.8
